autorecipes/__init__.py
autorecipes/cmake.py
autorecipes/data/configure/CMakeLists.txt
autorecipes/data/configure/attributes.py.in
autorecipes/data/install/CMakeLists.txt
autorecipes/data/install/cpp_info.py.in
autorecipes/descriptors.py
autorecipes/descriptors.pyi
autorecipes/python.py
autorecipes/stdlib.py
autorecipes/stubs/conans/__init__.pyi
autorecipes-0.2.0.dist-info/LICENSE
autorecipes-0.2.0.dist-info/WHEEL
autorecipes-0.2.0.dist-info/METADATA
autorecipes-0.2.0.dist-info/RECORD
