Metadata-Version: 2.1
Name: autorecipes
Version: 0.2.0
Summary: Generic Conan recipes for CMake and Python projects.
Home-page: https://github.com/thejohnfreeman/autorecipes/
License: ISC
Author: John Freeman
Author-email: jfreeman08@gmail.com
Requires-Python: >=3.6-dev,<4.0
Classifier: License :: OSI Approved
Classifier: Programming Language :: Python :: 3
Classifier: Programming Language :: Python :: 3.6
Classifier: Programming Language :: Python :: 3.7
Provides-Extra: docs
Requires-Dist: conan (>=1.14,<2.0)
Requires-Dist: sphinx (>=1.8,<2.0); extra == "docs"
Requires-Dist: sphinx_rtd_theme (>=0.4.3,<0.5.0); extra == "docs"
Requires-Dist: toml (>=0.10.0,<0.11.0)
Requires-Dist: typing_extensions (>=3.7,<4.0)
Project-URL: Documentation, https://autorecipes.readthedocs.io/
Project-URL: Repository, https://github.com/thejohnfreeman/autorecipes/
